mseep_waldur_mcp_server-0.1.4.dist-info/licenses/LICENSE.md
waldur_mcp_server/__init__.py
waldur_mcp_server/server.py
mseep_waldur_mcp_server-0.1.4.dist-info/METADATA
mseep_waldur_mcp_server-0.1.4.dist-info/WHEEL
mseep_waldur_mcp_server-0.1.4.dist-info/entry_points.txt
mseep_waldur_mcp_server-0.1.4.dist-info/top_level.txt
mseep_waldur_mcp_server-0.1.4.dist-info/RECORD
